persian_datetime_converter/__init__.py
persian_datetime_converter/converter.py
persian_datetime_converter-0.1.0.dist-info/LICENSE
persian_datetime_converter-0.1.0.dist-info/METADATA
persian_datetime_converter-0.1.0.dist-info/WHEEL
persian_datetime_converter-0.1.0.dist-info/top_level.txt
persian_datetime_converter-0.1.0.dist-info/RECORD
