Metadata-Version: 2.1
Name: persian-datetime-converter
Version: 0.1.0
Summary: Convert Python datetime objects to Persian (Jalali) calendar dates.
Home-page: https://github.com/bahmany/persian_datetime_converter
Author: Mohammad Reza Bahmani
Author-email: bahmanymb@gmail.com
License: MIT
Platform: UNKNOWN
Classifier: Development Status :: 4 - Beta
Classifier: Intended Audience :: Developers
Classifier: License :: OSI Approved :: MIT License
Classifier: Programming Language :: Python :: 3
Classifier: Programming Language :: Python :: 3.8
Classifier: Programming Language :: Python :: 3.9
Classifier: Programming Language :: Python :: 3.10
Requires-Python: >=3.8
License-File: LICENSE
